{"name": "Ukraińscy_politycy", "id": 101848, "predecessors": [{"name": "Polityka_Ukrainy", "id": 481937}, {"name": "Kategorie", "id": 1382275}], "successors": [{"name": "Ukraińscy_ministrowie", "id": 1283431}, {"name": "Ukraińscy_samorządowcy", "id": 1665593}, {"name": "Członkowie_Ukraińskiej_Centralnej_Rady", "id": 2714953}, {"name": "Ukraińscy_socjaliści", "id": 2775204}, {"name": "Kandydaci_na_urząd_prezydenta_Ukrainy", "id": 3329572}, {"name": "Ukraińscy_wiceministrowie", "id": 5759114}, {"name": "Ukraińscy_parlamentarzyści_II_Rzeczypospolitej", "id": 1188406}, {"name": "Deputowani_Rady_Najwyższej_Ukrainy", "id": 1278879}, {"name": "Ukraińscy_posłowie_do_Rady_Państwa_w_Wiedniu", "id": 1823517}, {"name": "Politycy_Naszej_Ukrainy", "id": 1062173}, {"name": "Politycy_Partii_Regionów", "id": 1062176}, {"name": "Politycy_Bloku_Julii_Tymoszenko", "id": 1062189}, {"name": "Członkowie_Organizacji_Ukraińskich_Nacjonalistów", "id": 1534291}, {"name": "Politycy_Ludowego_Ruchu_Ukrainy", "id": 1698691}, {"name": "Politycy_Batkiwszczyny", "id": 3127844}, {"name": "Politycy_Bloku_Petra_Poroszenki", "id": 3299141}]}