{"name": "Anatomia_głowy_i_szyi", "id": 1053654, "predecessors": [{"name": "Otorynolaryngologia", "id": 1053647}, {"name": "Anatomia_kręgowców", "id": 1589778}], "successors": [{"name": "Oko", "id": 1022601}, {"name": "Anatomia_narządu_słuchu_i_równowagi", "id": 1058222}, {"name": "Czaszka", "id": 1058398}, {"name": "Mięśnie_głowy_i_szyi", "id": 1425391}, {"name": "Przestrzenie_głowy_i_szyi", "id": 1425422}, {"name": "Nerwy_głowy_i_szyi", "id": 1425433}, {"name": "Naczynia_głowy_i_szyi", "id": 1425472}, {"name": "Jama_ustna", "id": 1257279}]}