{"name": "Rodziny_językowe", "id": 1122128, "predecessors": [{"name": "Językoznawstwo_historyczno-porównawcze", "id": 1010439}, {"name": "Językoznawstwo", "id": 66185}], "successors": [{"name": "Języki_indoeuropejskie", "id": 68626}, {"name": "Języki_kaukaskie", "id": 124120}, {"name": "Języki_austronezyjskie", "id": 164122}, {"name": "Języki_nigero-kongijskie", "id": 619351}, {"name": "Języki_autochtoniczne_Ameryki", "id": 749966}, {"name": "Języki_australijskie", "id": 1342409}, {"name": "Język_chiński", "id": 131094}, {"name": "Języki_semickie", "id": 125918}, {"name": "Języki_ugrofińskie", "id": 124376}]}