{"name": "Chrześcijaństwo_starożytne", "id": 125679, "predecessors": [{"name": "Historia_chrześcijaństwa", "id": 112504}, {"name": "Religioznawstwo", "id": 63676}], "successors": [{"name": "Patrystyka", "id": 444773}, {"name": "Postacie_Nowego_Testamentu", "id": 1284250}, {"name": "Apostołowie", "id": 1476916}, {"name": "Pisarze_wczesnochrześcijańscy", "id": 3444286}, {"name": "Męczennicy_wczesnochrześcijańscy", "id": 3477765}, {"name": "Literatura_gnostycka", "id": 1890501}, {"name": "Architektura_wczesnochrześcijańska", "id": 4395126}]}