{"name": "Rumuńscy_politycy", "id": 126237, "predecessors": [{"name": "Kategorie", "id": 1382275}], "successors": [{"name": "Premierzy_Rumunii", "id": 859085}, {"name": "Rumuńscy_ministrowie", "id": 1708911}, {"name": "Rumuńscy_samorządowcy", "id": 1783202}, {"name": "Rumuńscy_komuniści", "id": 1985977}, {"name": "Politycy_Partii_Demokratyczno-Liberalnej", "id": 3097975}, {"name": "Politycy_Partii_Socjaldemokratycznej_(Rumunia)", "id": 3097981}, {"name": "Politycy_Partii_Narodowo-Liberalnej_(Rumunia)", "id": 3097983}, {"name": "Rumuńscy_posłowie_do_Parlamentu_Europejskiego", "id": 891619}, {"name": "Rumuńscy_posłowie_do_Izby_Deputowanych", "id": 1708913}, {"name": "Rumuńscy_senatorowie", "id": 1708951}]}