{"name": "Rewolucja_francuska", "id": 1389435, "predecessors": [{"name": "Antyklerykalizm", "id": 192628}, {"name": "Francja_w_XVIII_wieku", "id": 1374108}, {"name": "Kategorie", "id": 1382275}, {"name": "Historia_Francji", "id": 65219}], "successors": [{"name": "Postacie_rewolucji_francuskiej", "id": 1462496}, {"name": "Ofiary_rewolucji_francuskiej", "id": 2261764}, {"name": "Uczestnicy_francuskich_wojen_rewolucyjnych", "id": 4841659}, {"name": "Ofiary_prześladowań_antykatolickich_(rewolucja_francuska)", "id": 2816577}]}