{"name": "Szablony_Fb", "id": 1652803, "predecessors": [{"name": "Szablony_piłkarskie", "id": 487733}], "successors": [{"name": "Drużyny_Fb_z_Anglii", "id": 1652802}, {"name": "Drużyny_Fb_z_Niemiec", "id": 1653670}, {"name": "Drużyny_Fb_z_Włoch", "id": 1654342}, {"name": "Drużyny_Fb_z_Polski", "id": 1655457}, {"name": "Drużyny_Fb_z_Hiszpanii", "id": 1657083}, {"name": "Drużyny_Fb_z_Francji", "id": 1657190}, {"name": "Drużyny_Fb_z_Rosji", "id": 1682110}, {"name": "Drużyny_Fb_z_Rumunii", "id": 1682214}, {"name": "Drużyny_Fb_z_Węgier", "id": 1683650}, {"name": "Drużyny_Fb_z_Portugalii", "id": 1684456}, {"name": "Drużyny_Fb_z_Grecji", "id": 1684495}, {"name": "Drużyny_Fb_z_Holandii", "id": 1684504}, {"name": "Drużyny_Fb_z_Ukrainy", "id": 1684506}, {"name": "Drużyny_Fb_z_Białorusi", "id": 1689988}, {"name": "Drużyny_Fb_z_Gruzji", "id": 1690295}, {"name": "Drużyny_Fb_z_Litwy", "id": 1690298}, {"name": "Drużyny_Fb_z_Azerbejdżanu", "id": 1690373}, {"name": "Drużyny_Fb_z_Szkocji", "id": 1690667}, {"name": "Drużyny_Fb_z_Mołdawii", "id": 1691681}, {"name": "Drużyny_Fb_z_Czech", "id": 1692803}, {"name": "Drużyny_Fb_z_Bułgarii", "id": 1695486}, {"name": "Drużyny_Fb_z_Malty", "id": 1696393}, {"name": "Drużyny_Fb_ze_Słowacji", "id": 1707855}, {"name": "Drużyny_Fb_z_Chorwacji", "id": 1716531}, {"name": "Drużyny_Fb_z_Albanii", "id": 1716540}, {"name": "Drużyny_Fb_z_Norwegii", "id": 1716541}, {"name": "Drużyny_Fb_z_Serbii", "id": 1716562}, {"name": "Drużyny_Fb_z_Bośni_i_Hercegowiny", "id": 1716571}, {"name": "Drużyny_Fb_z_Wysp_Owczych", "id": 1716576}, {"name": "Drużyny_Fb_z_Cypru", "id": 1716580}, {"name": "Drużyny_Fb_z_Danii", "id": 1716585}, {"name": "Drużyny_Fb_ze_Szwecji", "id": 1716592}, {"name": "Drużyny_Fb_z_Islandii", "id": 1716608}, {"name": "Drużyny_Fb_z_Łotwy", "id": 1716625}, {"name": "Drużyny_Fb_z_Luksemburga", "id": 1716628}, {"name": "Drużyny_Fb_z_Austrii", "id": 1716639}, {"name": "Drużyny_Fb_z_Finlandii", "id": 1716646}, {"name": "Drużyny_Fb_z_Walii", "id": 1716651}, {"name": "Drużyny_Fb_z_Izraela", "id": 1716658}, {"name": "Drużyny_Fb_z_Macedonii", "id": 1716876}, {"name": "Drużyny_Fb_ze_Szwajcarii", "id": 1729534}, {"name": "Drużyny_Fb_z_Belgii", "id": 1730075}, {"name": "Drużyny_Fb_z_Turcji", "id": 1732760}, {"name": "Drużyny_Fb_z_Brazylii", "id": 1766141}, {"name": "Drużyny_Fb_z_Meksyku", "id": 1766315}, {"name": "Drużyny_Fb_z_Iranu", "id": 2247097}, {"name": "Drużyny_Fb_ze_Stanów_Zjednoczonych", "id": 2737670}, {"name": "Drużyny_Fb_z_Chin", "id": 3597958}, {"name": "Drużyny_Fb_z_Kosowa", "id": 4298263}]}