{"name": "Ludzie_związani_z_Sofią", "id": 1707772, "predecessors": [{"name": "Kategorie", "id": 1382275}], "successors": [{"name": "Piłkarze_Lewskiego_Sofia", "id": 567884}, {"name": "Piłkarze_CSKA_Sofia", "id": 568254}, {"name": "Piłkarze_Łokomotiwu_Sofia", "id": 2722294}, {"name": "Trenerzy_piłkarzy_Lewskiego_Sofia", "id": 2760291}, {"name": "Piłkarze_Sławii_Sofia", "id": 2905107}, {"name": "Ludzie_urodzeni_w_Sofii", "id": 3881562}, {"name": "Pisarze_związani_z_Sofią", "id": 4219562}, {"name": "Wykładowcy_Uniwersytetu_Sofijskiego", "id": 4458419}, {"name": "Absolwenci_Uniwersytetu_Gospodarki_Narodowej_i_Światowej_w_Sofii", "id": 5380107}]}