{"name": "Niemieccy_piłkarze", "id": 181391, "predecessors": [{"name": "Niemcy_(biografie)", "id": 116863}, {"name": "Dyscypliny_sportowe", "id": 1030024}], "successors": [{"name": "Reprezentanci_Niemiec_w_piłce_nożnej", "id": 1272785}, {"name": "Niemieccy_piłkarze_polskiego_pochodzenia", "id": 1907337}, {"name": "Reprezentanci_Niemiec_U-21_w_piłce_nożnej", "id": 5527414}, {"name": "Reprezentanci_Niemiec_U-20_w_piłce_nożnej", "id": 5528227}, {"name": "Reprezentanci_Niemiec_U-23_w_piłce_nożnej", "id": 5541549}, {"name": "Reprezentanci_Niemieckiej_Republiki_Demokratycznej_w_piłce_nożnej", "id": 2708321}]}