{"name": "Ludzie_związani_z_Rzymem", "id": 1880973, "predecessors": [{"name": "Kategorie", "id": 1382275}], "successors": [{"name": "Wykładowcy_uczelni_w_Rzymie", "id": 3491111}, {"name": "Absolwenci_uczelni_w_Rzymie", "id": 3491113}, {"name": "Ludzie_urodzeni_w_Rzymie", "id": 3682987}, {"name": "Pochowani_na_Cmentarzu_Campo_Verano_w_Rzymie", "id": 2083087}, {"name": "Pisarze_związani_z_Rzymem", "id": 4009984}, {"name": "Malarze_związani_z_Rzymem", "id": 4880864}, {"name": "Piłkarze_AS_Roma", "id": 564045}, {"name": "Piłkarze_S.S._Lazio", "id": 1205236}, {"name": "Trenerzy_piłkarzy_AS_Roma", "id": 2771139}]}