{"name": "Partie_socjalistyczne_i_socjaldemokratyczne", "id": 2630814, "predecessors": [{"name": "Kategorie", "id": 1382275}, {"name": "Socjalizm", "id": 190668}], "successors": [{"name": "Socjaliści", "id": 503139}, {"name": "Polskie_partie_socjalistyczne", "id": 2938202}, {"name": "Politycy_SDKPiL", "id": 791154}, {"name": "Politycy_Litewskiej_Partii_Socjaldemokratycznej", "id": 1476589}, {"name": "Politycy_Smeru", "id": 1668055}, {"name": "Politycy_Czeskiej_Partii_Socjaldemokratycznej", "id": 1668398}, {"name": "Politycy_Węgierskiej_Partii_Socjalistycznej", "id": 1709214}, {"name": "Politycy_Hiszpańskiej_Socjalistycznej_Partii_Robotniczej", "id": 1726896}, {"name": "Politycy_Socjaldemokratycznej_Partii_Finlandii", "id": 1804797}, {"name": "Politycy_Partii_Socjalistycznej_(Flandria)", "id": 1857373}, {"name": "Politycy_Szwedzkiej_Socjaldemokratycznej_Partii_Robotniczej", "id": 1891201}, {"name": "Politycy_Panhelleńskiego_Ruchu_Socjalistycznego", "id": 1982530}, {"name": "Politycy_Partii_Pracy_(Holandia)", "id": 3031515}, {"name": "Politycy_Partii_Pracy_(Irlandia)", "id": 3031518}, {"name": "Politycy_Partii_Pracy_(Norwegia)", "id": 3031519}, {"name": "Politycy_Partii_Pracy_(Wielka_Brytania)", "id": 3031520}, {"name": "Politycy_Partii_Socjalistycznej_(Portugalia)", "id": 3031535}, {"name": "Politycy_Socjaldemokratycznej_Partii_Austrii", "id": 3041078}, {"name": "Politycy_Mapai", "id": 3508842}, {"name": "Politycy_Izraelskiej_Partii_Pracy", "id": 3508849}, {"name": "Politycy_Koalicji_Pracy", "id": 3602104}, {"name": "Politycy_Mapam", "id": 3508877}]}