{"name": "Sport_w_Bawarii", "id": 2936610, "predecessors": [{"name": "Kategorie", "id": 1382275}], "successors": [{"name": "Piłkarze_SpVgg_Greuther_Fürth", "id": 968353}, {"name": "Piłkarze_SpVgg_Unterhaching", "id": 1233008}, {"name": "Piłkarze_SV_Wacker_Burghausen", "id": 1373026}, {"name": "Sport_w_Oberstdorfie", "id": 2936699}, {"name": "Piłkarze_FC_Augsburg", "id": 1330884}, {"name": "Piłkarze_FC_Ingolstadt_04", "id": 2207049}, {"name": "Turniej_Czterech_Skoczni", "id": 569731}, {"name": "Puchar_Świata_w_skokach_narciarskich_w_Garmisch-Partenkirchen", "id": 4196061}, {"name": "Mistrzostwa_Europy_w_Lekkoatletyce_2022", "id": 5329861}]}