{"name": "Entomologia", "id": 403091, "predecessors": [{"name": "Kategorie", "id": 1382275}], "successors": [{"name": "Czasopisma_entomologiczne", "id": 1704082}, {"name": "Ekologia_owadów", "id": 3532387}, {"name": "Ważki", "id": 450401}, {"name": "Wymarłe_owady", "id": 1169952}, {"name": "Listy_owadów", "id": 5075602}, {"name": "Szarańczowate", "id": 862031}, {"name": "Pasikonikowate", "id": 862100}, {"name": "Skorkowate", "id": 3235901}, {"name": "Pilarzowate", "id": 882547}, {"name": "Gąsienicznikowate", "id": 3446827}, {"name": "Męczelkowate", "id": 3502242}, {"name": "Pergidae", "id": 5178624}, {"name": "Pszczołowate", "id": 1607669}, {"name": "Smuklikowate", "id": 3589337}, {"name": "Mrówkowate", "id": 1673482}, {"name": "Błonkówki_Ameryki_Południowej", "id": 3230815}, {"name": "Błonkówki_Australii", "id": 3241993}, {"name": "Błonkówki_Azji", "id": 3264618}, {"name": "Błonkówki_Ameryki_Północnej", "id": 3264622}, {"name": "Błonkówki_Europy", "id": 3264624}, {"name": "Błonkówki_Afryki", "id": 3264626}, {"name": "Limnephilidae", "id": 1377898}, {"name": "Leptoceridae", "id": 1377955}, {"name": "Chruściki_Europy", "id": 3985041}, {"name": "Chrząszcze_Azji", "id": 3233539}, {"name": "Ważki_Azji", "id": 3531515}, {"name": "Motyle_Azji", "id": 3981539}, {"name": "Pluskwiaki_Azji", "id": 3981684}, {"name": "Prostoskrzydłe_Azji", "id": 3982454}, {"name": "Muchówki_Azji", "id": 3982532}, {"name": "Wszy_i_wszoły_Azji", "id": 3985809}, {"name": "Motyle_Ameryki_Południowej", "id": 3229258}, {"name": "Chrząszcze_Ameryki_Południowej", "id": 3229324}, {"name": "Pluskwiaki_Ameryki_Południowej", "id": 3230707}, {"name": "Ważki_Ameryki_Południowej", "id": 3230979}, {"name": "Muchówki_Ameryki_Południowej", "id": 3231978}, {"name": "Wszy_i_wszoły_Ameryki_Południowej", "id": 3985818}, {"name": "Chrząszcze_Ameryki_Północnej", "id": 3229326}, {"name": "Ważki_Ameryki_Północnej", "id": 3232232}, {"name": "Motyle_Ameryki_Północnej", "id": 3981542}, {"name": "Pluskwiaki_Ameryki_Północnej", "id": 3981682}, {"name": "Muchówki_Ameryki_Północnej", "id": 3982548}, {"name": "Wszy_i_wszoły_Ameryki_Północnej", "id": 3985814}, {"name": "Ważki_Afryki", "id": 3531536}, {"name": "Ważki_Australii", "id": 3531550}, {"name": "Ważki_Europy", "id": 3987440}, {"name": "Ważki_Oceanii", "id": 5247251}, {"name": "Biegaczowate", "id": 849621}, {"name": "Pływakowate", "id": 850078}, {"name": "Krętakowate", "id": 2194749}, {"name": "Bogatkowate", "id": 850727}, {"name": "Omomiłkowate", "id": 850745}, {"name": "Kózkowate", "id": 850761}, {"name": "Stonkowate", "id": 850858}, {"name": "Ryjkowcowate", "id": 851089}, {"name": "Biedronkowate", "id": 851310}, {"name": "Sprężykowate", "id": 851721}, {"name": "Kałużnicowate", "id": 851924}, {"name": "Oleicowate", "id": 852247}, {"name": "Tutkarzowate", "id": 852432}, {"name": "Kusakowate", "id": 853307}, {"name": "Czarnuchowate", "id": 853346}, {"name": "Skórnikowate_(owady)", "id": 2196002}, {"name": "Karmazynkowate", "id": 2224204}, {"name": "Poświętnikowate", "id": 3102489}, {"name": "Grzybinkowate", "id": 3139338}, {"name": "Nakwiatkowate", "id": 3177791}, {"name": "Chrząszcze_Filipin", "id": 3093325}, {"name": "Chrząszcze_Tajlandii", "id": 3093334}, {"name": "Chrząszcze_Indonezji", "id": 3093337}, {"name": "Chrząszcze_Wietnamu", "id": 3093338}, {"name": "Chrząszcze_Malezji", "id": 3093340}, {"name": "Chrząszcze_Laosu", "id": 3093341}, {"name": "Chrząszcze_Indii", "id": 3093349}, {"name": "Chrząszcze_Mjanmy", "id": 3093355}, {"name": "Chrząszcze_Nepalu", "id": 3093357}, {"name": "Chrząszcze_Chin", "id": 3093359}, {"name": "Chrząszcze_Tajwanu", "id": 3093366}, {"name": "Chrząszcze_Japonii", "id": 3093369}, {"name": "Chrząszcze_Madagaskaru", "id": 3076580}, {"name": "Chrząszcze_Nowej_Zelandii", "id": 3111893}, {"name": "Chrząszcze_Australii", "id": 3114273}, {"name": "Chrząszcze_Makaronezji", "id": 3278297}, {"name": "Chrząszcze_Afryki", "id": 3278303}, {"name": "Chrząszcze_Europy", "id": 3278309}, {"name": "Chrząszcze_Egiptu", "id": 3278327}, {"name": "Chrząszcze_Turcji", "id": 3278340}, {"name": "Chrząszcze_Rosji", "id": 3278346}, {"name": "Rusałkowate", "id": 867485}, {"name": "Bielinkowate", "id": 878272}, {"name": "Sówkowate", "id": 878516}, {"name": "Paziowate", "id": 879190}, {"name": "Modraszkowate", "id": 879396}, {"name": "Garbatkowate", "id": 880412}, {"name": "Miernikowcowate", "id": 880934}, {"name": "Lecithoceridae", "id": 3586306}, {"name": "Motyle_Australii", "id": 3246887}, {"name": "Motyle_Europy", "id": 3981540}, {"name": "Motyle_Afryki", "id": 3981541}, {"name": "Tasznikowate", "id": 865935}, {"name": "Tarczówkowate", "id": 866380}, {"name": "Zajadkowate", "id": 867096}, {"name": "Ziemikowate", "id": 868024}, {"name": "Pluskwiaki_Europy", "id": 3981686}, {"name": "Pluskwiaki_Afryki", "id": 3981687}, {"name": "Bujankowate", "id": 859821}, {"name": "Rączycowate", "id": 861330}, {"name": "Wywilżnowate", "id": 3139192}, {"name": "Lwinkowate", "id": 3363851}, {"name": "Błotniszkowate", "id": 3587362}, {"name": "Sphaeroceridae", "id": 4317040}, {"name": "Muchówki_Europy", "id": 3982535}, {"name": "Muchówki_Afryki", "id": 3982537}, {"name": "Niedźwiedziówkowate", "id": 879907}, {"name": "Prostoskrzydłe_Europy", "id": 3982456}]}