{"name": "Ichtiologia", "id": 505772, "predecessors": [{"name": "Hydrobiologia", "id": 405212}, {"name": "Kategorie", "id": 1382275}], "successors": [{"name": "Anatomia_ryb", "id": 3459796}, {"name": "Żarłaczowate", "id": 923794}, {"name": "Okoniokształtne", "id": 509159}, {"name": "Głowaczowate", "id": 650610}, {"name": "Żmijakowate", "id": 631393}, {"name": "Kongerowate", "id": 939546}, {"name": "Łososiowate", "id": 1772735}, {"name": "Wężorowate", "id": 1795786}, {"name": "Dorszowate", "id": 517861}, {"name": "Piękniczkowate", "id": 515170}, {"name": "Strumieniakowate", "id": 1853900}, {"name": "Nothobranchiidae", "id": 1856058}, {"name": "Ryby_akwariowe", "id": 519253}, {"name": "Karpiowate", "id": 499938}, {"name": "Kąsaczowate", "id": 520285}, {"name": "Hypostominae", "id": 4390258}, {"name": "Loricariinae", "id": 4397630}]}