{"name": "Jednostki_podziału_administracyjnego", "id": 517020, "predecessors": [{"name": "Administracja_publiczna", "id": 202934}], "successors": [{"name": "Kasztelanie", "id": 1781312}, {"name": "Województwo_małopolskie", "id": 72915}, {"name": "Województwo_lubuskie", "id": 105228}, {"name": "Województwo_śląskie", "id": 105229}, {"name": "Województwo_pomorskie", "id": 105232}, {"name": "Województwo_zachodniopomorskie", "id": 105233}, {"name": "Województwo_wielkopolskie", "id": 105236}, {"name": "Województwo_kujawsko-pomorskie", "id": 105243}, {"name": "Herby_miast_województwa_dolnośląskiego", "id": 963584}, {"name": "Radni_sejmiku_województwa_dolnośląskiego", "id": 1139285}, {"name": "Członkowie_zarządu_województwa_dolnośląskiego", "id": 1139299}, {"name": "Herby_gmin_województwa_dolnośląskiego", "id": 1202199}, {"name": "Odznaczeni_Odznaką_Honorową_Zasłużony_dla_Województwa_Dolnośląskiego", "id": 3913195}, {"name": "Herby_miast_województwa_świętokrzyskiego", "id": 963555}, {"name": "Radni_sejmiku_województwa_świętokrzyskiego", "id": 1148378}, {"name": "Herby_gmin_województwa_świętokrzyskiego", "id": 1619899}, {"name": "Odznaczeni_Odznaką_Honorową_Województwa_Świętokrzyskiego", "id": 4780457}, {"name": "Herby_miast_województwa_łódzkiego", "id": 963020}, {"name": "Herby_gmin_województwa_łódzkiego", "id": 1202186}, {"name": "Herby_miast_województwa_lubelskiego", "id": 962691}, {"name": "Herby_gmin_województwa_lubelskiego", "id": 1202205}, {"name": "Architektura_neogotycka_w_województwie_lubelskim", "id": 3537940}, {"name": "Architektura_renesansowa_w_województwie_lubelskim", "id": 3570295}, {"name": "Architektura_barokowa_w_województwie_lubelskim", "id": 3570307}, {"name": "Synagogi_w_województwie_lubelskim", "id": 641254}, {"name": "Zabytkowe_klasztory_katolickie_w_województwie_lubelskim", "id": 4682721}, {"name": "Cmentarze_katolickie_w_województwie_lubelskim", "id": 2552285}, {"name": "Cmentarze_żydowskie_w_województwie_lubelskim", "id": 2592552}, {"name": "Muzea_w_województwie_lubelskim", "id": 948803}, {"name": "Kultura_w_Lublinie", "id": 1327055}, {"name": "Radni_sejmiku_województwa_lubelskiego", "id": 1148339}, {"name": "Wojewodowie_lubelscy_(I_Rzeczpospolita)", "id": 2179200}, {"name": "Architektura_gotyku_w_województwie_łódzkim", "id": 2446212}, {"name": "Architektura_neogotycka_w_województwie_łódzkim", "id": 3537944}, {"name": "Architektura_barokowa_w_województwie_łódzkim", "id": 3579922}, {"name": "Młyny_w_województwie_łódzkim", "id": 5692114}, {"name": "Synagogi_w_województwie_łódzkim", "id": 641279}, {"name": "Zabytkowe_klasztory_katolickie_w_województwie_łódzkim", "id": 4682747}, {"name": "Pochowani_na_Starym_Cmentarzu_w_Łodzi", "id": 1346412}, {"name": "Radni_sejmiku_województwa_łódzkiego", "id": 1148359}, {"name": "Kultura_w_Łodzi", "id": 499174}, {"name": "Muzea_w_województwie_łódzkim", "id": 878703}, {"name": "Cmentarze_żydowskie_w_województwie_świętokrzyskim", "id": 2595923}, {"name": "Muzea_w_województwie_świętokrzyskim", "id": 878738}, {"name": "Drewniane_kościoły_w_województwie_lubelskim", "id": 1412994}, {"name": "Zabytkowe_kościoły_w_powiecie_bialskim", "id": 3937305}, {"name": "Flagi_stanowe_Stanów_Zjednoczonych", "id": 1164041}, {"name": "Flagi_jednostek_samorządu_terytorialnego_w_Polsce", "id": 5428630}, {"name": "Przedsiębiorstwa_w_Łodzi", "id": 3151324}, {"name": "Drogi_wojewódzkie_w_województwie_świętokrzyskim", "id": 4028052}, {"name": "Ulice_i_place_w_Kielcach", "id": 623126}, {"name": "Drogi_wojewódzkie_w_województwie_dolnośląskim", "id": 4027481}, {"name": "Drogi_wojewódzkie_w_województwie_lubelskim", "id": 4031583}, {"name": "Stacje_i_przystanki_kolejowe_we_Wrocławiu", "id": 1586072}, {"name": "Drewniane_cerkwie_w_województwie_lubelskim", "id": 3443016}, {"name": "Ludzie_związani_z_Kielcami", "id": 263329}, {"name": "Ludzie_związani_z_Ostrowcem_Świętokrzyskim", "id": 1076447}, {"name": "Ludzie_związani_z_Sandomierzem", "id": 1148549}, {"name": "Ludzie_związani_ze_Skarżyskiem-Kamienną", "id": 1907792}, {"name": "Geografia_Starachowic", "id": 3686444}, {"name": "Kletno", "id": 4069621}, {"name": "Ludzie_związani_z_Wrocławiem", "id": 195970}, {"name": "Historia_Wrocławia", "id": 479093}, {"name": "Kultura_we_Wrocławiu", "id": 722396}, {"name": "Ludzie_związani_z_Wałbrzychem", "id": 980500}, {"name": "Ludzie_związani_z_Głogowem", "id": 149155}, {"name": "Ludzie_związani_ze_Świdnicą", "id": 793808}, {"name": "Ludzie_związani_z_Kłodzkiem", "id": 1413828}, {"name": "Geografia_Szklarskiej_Poręby", "id": 3554633}, {"name": "Geografia_Karpacza", "id": 3554628}, {"name": "Ludzie_związani_z_Lublinem", "id": 256917}, {"name": "Przedsiębiorstwa_w_Lublinie", "id": 1291843}, {"name": "Ludzie_związani_z_Białą_Podlaską", "id": 1079175}, {"name": "Ludzie_związani_z_Chełmem", "id": 732929}, {"name": "Ludzie_związani_z_Zamościem", "id": 984289}, {"name": "Ludzie_związani_z_Biłgorajem", "id": 915389}, {"name": "Ludzie_związani_z_Puławami", "id": 1725752}, {"name": "Ludzie_związani_z_Kraśnikiem", "id": 3320244}, {"name": "Ludzie_związani_z_Łukowem", "id": 888813}, {"name": "Ludzie_związani_z_Łodzią", "id": 100708}, {"name": "Historia_Łodzi", "id": 638415}, {"name": "Ludzie_związani_z_Piotrkowem_Trybunalskim", "id": 929616}, {"name": "Ludzie_związani_z_Pabianicami", "id": 1078201}, {"name": "Ludzie_związani_z_Kutnem", "id": 1790654}, {"name": "Ludzie_związani_z_Tomaszowem_Mazowieckim", "id": 1545984}, {"name": "Ludzie_związani_z_Łowiczem", "id": 785941}, {"name": "Ludzie_związani_z_Wieluniem", "id": 993757}, {"name": "Ludzie_związani_ze_Skierniewicami", "id": 1725960}, {"name": "Ludzie_związani_z_Sieradzem", "id": 1058969}, {"name": "Ludzie_związani_ze_Zgierzem", "id": 1415601}, {"name": "Filmy_kręcone_w_Piotrkowie_Trybunalskim", "id": 3665051}, {"name": "Ludzie_urodzeni_w_Radomsku", "id": 3723583}, {"name": "Ludzie_urodzeni_w_Łęczycy", "id": 3736011}, {"name": "Ludzie_urodzeni_w_Opocznie", "id": 3731168}, {"name": "Ludzie_urodzeni_w_Rawie_Mazowieckiej", "id": 3735748}, {"name": "Ludzie_urodzeni_w_Bełchatowie", "id": 3723584}, {"name": "Ludzie_urodzeni_w_Zduńskiej_Woli", "id": 3723588}, {"name": "Ludzie_urodzeni_w_Brzezinach", "id": 3736100}, {"name": "Ludzie_urodzeni_w_Hrubieszowie", "id": 3732348}, {"name": "Ludzie_urodzeni_w_Międzyrzecu_Podlaskim", "id": 3735777}, {"name": "Ludzie_urodzeni_w_Krasnymstawie", "id": 3732297}, {"name": "Ludzie_urodzeni_w_Radzyniu_Podlaskim", "id": 3735890}, {"name": "Ludzie_urodzeni_w_Tomaszowie_Lubelskim", "id": 3732281}, {"name": "Uczestnicy_bitwy_pod_Tomaszowem_Lubelskim_(1939)", "id": 3884553}, {"name": "Ludzie_związani_z_Nową_Rudą", "id": 1540440}, {"name": "Piastowie_wrocławscy_i_legnicko-brzescy", "id": 1585959}, {"name": "Ludzie_urodzeni_w_Legnicy", "id": 3723627}, {"name": "Ludzie_urodzeni_w_Jeleniej_Górze", "id": 3723878}, {"name": "Ludzie_urodzeni_w_Kamiennej_Górze", "id": 3732280}, {"name": "Ludzie_urodzeni_w_Dzierżoniowie", "id": 3724029}, {"name": "Ludzie_urodzeni_w_Zgorzelcu", "id": 3727527}, {"name": "Ludzie_urodzeni_w_Oleśnicy", "id": 3724016}, {"name": "Ludzie_urodzeni_w_Bolesławcu", "id": 3724003}, {"name": "Ludzie_urodzeni_w_Ząbkowicach_Śląskich", "id": 3735990}, {"name": "Ludzie_urodzeni_w_Lubinie", "id": 3723865}, {"name": "Trenerzy_piłkarzy_Zagłębia_Lubin", "id": 2769336}, {"name": "Ludzie_urodzeni_w_Oławie", "id": 3727525}, {"name": "Ludzie_urodzeni_w_Pińczowie", "id": 3747404}, {"name": "Ludzie_urodzeni_w_Starachowicach", "id": 3723679}, {"name": "Ludzie_urodzeni_w_Staszowie", "id": 3735997}, {"name": "Ludzie_urodzeni_w_Jędrzejowie", "id": 3735978}, {"name": "Piłkarze_Górnika_Łęczna", "id": 640790}, {"name": "Ludzie_urodzeni_w_Łasku", "id": 3732366}, {"name": "Posłowie_na_sejm_parczewski_1564", "id": 5300351}, {"name": "Ludzie_urodzeni_w_Opatowie", "id": 3764312}, {"name": "Okręgi_w_Albanii", "id": 138157}, {"name": "Okręgi_w_Rumunii", "id": 139543}, {"name": "Okręgi_Francji", "id": 2260111}, {"name": "Okręgi_w_Belgii", "id": 5682009}, {"name": "Dawne_rejony_Białorusi", "id": 1776643}, {"name": "Filmy_kręcone_w_Łodzi", "id": 3270017}, {"name": "Filmy_kręcone_w_Lublinie", "id": 5183258}, {"name": "Dzielnice_i_osiedla_Piotrkowa_Trybunalskiego", "id": 1282715}, {"name": "Dzielnice_i_osiedla_Bełchatowa", "id": 1520111}, {"name": "Ulice_w_Zamościu", "id": 4902667}, {"name": "Dzielnice_i_osiedla_Skarżyska-Kamiennej", "id": 1574565}, {"name": "Ludzie_urodzeni_w_Ozorkowie", "id": 3731593}, {"name": "Zabytkowe_cerkwie_w_powiecie_bialskim", "id": 3508315}, {"name": "Cmentarze_prawosławne_w_powiecie_hrubieszowskim", "id": 3678294}, {"name": "Ludzie_urodzeni_w_Lubartowie", "id": 3730557}, {"name": "Absolwenci_Wyższej_Oficerskiej_Szkoły_Lotniczej_w_Dęblinie", "id": 2374822}, {"name": "Absolwenci_Szkoły_Podchorążych_Lotnictwa_w_Dęblinie", "id": 2792810}, {"name": "Radni_Łodzi_(II_Rzeczpospolita)", "id": 3907598}, {"name": "Architektura_neorenesansowa_w_Łodzi", "id": 3936596}, {"name": "Architektura_modernizmu_w_Łodzi", "id": 3938439}, {"name": "Cmentarze_z_I_wojny_światowej_w_województwie_lubelskim", "id": 1679724}, {"name": "Posłowie_z_okręgu_Legnica", "id": 439366}, {"name": "Posłowie_z_okręgu_Legnica_(PRL)", "id": 1757315}, {"name": "Ziemia_sieradzka", "id": 1790624}, {"name": "Parafie_cywilne_w_stanie_Luizjana", "id": 3017011}, {"name": "Civil_parishes_w_hrabstwie_Northumberland", "id": 3552949}, {"name": "Civil_parishes_w_hrabstwie_Suffolk", "id": 3552966}, {"name": "Civil_parishes_w_hrabstwie_Devon", "id": 3553771}, {"name": "Civil_parishes_w_hrabstwie_Lincolnshire", "id": 3553809}, {"name": "Civil_parishes_w_hrabstwie_Essex", "id": 3554009}, {"name": "Civil_parishes_w_hrabstwie_Nottinghamshire", "id": 3554829}, {"name": "Civil_parishes_w_hrabstwie_Oxfordshire", "id": 3556938}, {"name": "Civil_parishes_w_hrabstwie_Worcestershire", "id": 3557089}, {"name": "Civil_parishes_w_hrabstwie_Warwickshire", "id": 3557385}, {"name": "Civil_parishes_w_hrabstwie_Lancashire", "id": 3557424}, {"name": "Civil_parishes_w_hrabstwie_Cheshire", "id": 3558059}, {"name": "Civil_parishes_w_hrabstwie_Wiltshire", "id": 3558557}, {"name": "Civil_parishes_w_hrabstwie_Gloucestershire", "id": 3559029}, {"name": "Civil_parishes_w_hrabstwie_Staffordshire", "id": 3560232}, {"name": "Civil_parishes_w_hrabstwie_Shropshire", "id": 3560239}, {"name": "Civil_parishes_w_hrabstwie_North_Yorkshire", "id": 3561541}, {"name": "Civil_parishes_w_hrabstwie_Herefordshire", "id": 3562000}, {"name": "Civil_parishes_w_hrabstwie_Derbyshire", "id": 3562115}, {"name": "Civil_parishes_w_hrabstwie_Durham", "id": 3563417}, {"name": "Civil_parishes_w_hrabstwie_Cambridgeshire", "id": 3567472}, {"name": "Civil_parishes_w_hrabstwie_Berkshire", "id": 3568151}, {"name": "Civil_parishes_w_hrabstwie_West_Yorkshire", "id": 3569431}, {"name": "Civil_parishes_w_Kumbrii", "id": 3569614}, {"name": "Civil_parishes_w_hrabstwie_Dorset", "id": 3570094}, {"name": "Civil_parishes_w_hrabstwie_Hampshire", "id": 3570962}, {"name": "Civil_parishes_w_hrabstwie_Norfolk", "id": 3578901}, {"name": "Civil_parishes_w_hrabstwie_Kent", "id": 3586816}, {"name": "Civil_parishes_w_hrabstwie_Hertfordshire", "id": 3588917}, {"name": "Dawne_civil_parishes_Anglii", "id": 4161876}, {"name": "Parafie_rzymskokatolickie_w_Łodzi", "id": 1547703}, {"name": "Parafie_rzymskokatolickie_w_Lublinie", "id": 1558991}, {"name": "Kluby_piłkarskie_w_województwie_łódzkim", "id": 880745}, {"name": "Dawne_gromady_w_województwie_łódzkim", "id": 2838868}, {"name": "Wicewojewodowie_łódzcy", "id": 1811707}, {"name": "Gminy_w_Grecji", "id": 1591750}, {"name": "Gminy_w_Finlandii", "id": 1860348}, {"name": "Gminy_w_Słowenii", "id": 2162313}, {"name": "Gminy_w_Gwatemali", "id": 2920982}, {"name": "Gminy_we_Francji", "id": 3178924}, {"name": "Gminy_w_Kosowie", "id": 3578515}, {"name": "Gminy_w_Luksemburgu", "id": 5562019}, {"name": "Historyczne_gminy_w_Danii", "id": 1432791}, {"name": "Gminy_w_regionie_Västra_Götaland", "id": 2460061}, {"name": "Gminy_w_okręgu_Nordland", "id": 2194265}, {"name": "Gminy_w_okręgu_Møre_og_Romsdal", "id": 2205666}, {"name": "Gminy_w_okręgu_Trøndelag", "id": 4224336}, {"name": "Gminy_w_Estremadurze", "id": 1886646}, {"name": "Gminy_na_Balearach", "id": 1886748}, {"name": "Gminy_w_Kraju_Basków", "id": 1887071}, {"name": "Gminy_w_Galicji", "id": 1888461}, {"name": "Gminy_w_Asturii", "id": 1888489}, {"name": "Gminy_w_Kantabrii", "id": 2981689}, {"name": "Gminy_w_La_Rioja", "id": 2981869}, {"name": "Gminy_w_Nawarze", "id": 3032904}, {"name": "Gminy_na_Wyspach_Kanaryjskich", "id": 3032917}, {"name": "Gminy_w_Murcji", "id": 3032921}, {"name": "Gminy_w_stanie_Ohio", "id": 1188103}, {"name": "Gminy_(town)_w_stanie_Vermont", "id": 5486643}, {"name": "Gminy_w_Saksonii", "id": 1176472}, {"name": "Gminy_w_Badenii-Wirtembergii", "id": 1619782}, {"name": "Gminy_w_Meklemburgii-Pomorzu_Przednim", "id": 1619788}, {"name": "Dawne_gminy_w_Niemczech", "id": 2847333}, {"name": "Gminy_w_Bawarii", "id": 4789375}, {"name": "Gminy_w_Turyngii", "id": 4993717}, {"name": "Gminy_w_Brandenburgii", "id": 4993727}, {"name": "Gminy_w_Dolnej_Saksonii", "id": 4993744}, {"name": "Gminy_w_Hesji", "id": 4994195}, {"name": "Gminy_w_Nadrenii_Północnej-Westfalii", "id": 4994210}, {"name": "Gminy_w_Nadrenii-Palatynacie", "id": 4994216}, {"name": "Gminy_w_Saarze", "id": 4994222}, {"name": "Gminy_w_Saksonii-Anhalcie", "id": 4994236}, {"name": "Gminy_w_Szlezwiku-Holsztynie", "id": 4994240}, {"name": "Miejscowości_w_gminie_Alatskivi", "id": 2351684}, {"name": "Dawne_gminy_w_prowincji_Antwerpia", "id": 5712397}, {"name": "Dawne_gminy_w_Brabancji_Flamandzkiej", "id": 5723285}, {"name": "Dawne_gminy_we_Flandrii_Wschodniej", "id": 5730253}, {"name": "Dawne_gminy_we_Flandrii_Zachodniej", "id": 5742750}, {"name": "Dawne_gminy_w_Limburgii_(Belgia)", "id": 5752935}, {"name": "Dawne_gminy_w_Brabancji_Walońskiej", "id": 5761422}, {"name": "Dawne_gminy_w_Hainaut", "id": 5764626}, {"name": "Powiaty_w_Czechach", "id": 204403}, {"name": "Powiat_Segeberg", "id": 1625595}, {"name": "Powiat_Dithmarschen", "id": 1625601}, {"name": "Powiat_Herzogtum_Lauenburg", "id": 1625602}, {"name": "Powiat_Nordfriesland", "id": 1625604}, {"name": "Powiat_Ostholstein", "id": 1625606}, {"name": "Powiat_Pinneberg", "id": 1625607}, {"name": "Powiat_Plön", "id": 1625612}, {"name": "Powiat_Rendsburg-Eckernförde", "id": 1625613}, {"name": "Powiat_Schleswig-Flensburg", "id": 1625647}, {"name": "Powiat_Steinburg", "id": 1625650}, {"name": "Powiat_Stormarn", "id": 1625651}, {"name": "Gminy_w_rejonie_Florești", "id": 5140604}, {"name": "Prowincje_w_Turcji", "id": 142576}, {"name": "Prowincje_Indonezji", "id": 317867}, {"name": "Prowincje_Hiszpanii", "id": 518980}, {"name": "Prowincje_Tajlandii", "id": 751820}, {"name": "Prowincje_Wietnamu", "id": 1451047}, {"name": "Prowincje_Filipin", "id": 1896960}, {"name": "Prowincje_Dominikany", "id": 4241089}, {"name": "Junnan", "id": 1711946}, {"name": "Anhui", "id": 1711954}, {"name": "Hubei", "id": 1711961}, {"name": "Hebei", "id": 1711968}, {"name": "Rejony_na_Białorusi", "id": 602069}, {"name": "Rejony_obwodu_lwowskiego", "id": 1422235}, {"name": "Rejon_bohorodczański", "id": 2035750}, {"name": "Rejon_tłumacki", "id": 2035751}, {"name": "Rejon_doliński", "id": 2037575}, {"name": "Rejon_śniatyński", "id": 2038215}, {"name": "Rejon_kołomyjski", "id": 2038221}, {"name": "Rejon_wierchowiński", "id": 2039954}, {"name": "Rejon_tyśmienicki", "id": 2040011}, {"name": "Rejon_rożniatowski", "id": 2040426}, {"name": "Rejon_rohatyński", "id": 2040432}, {"name": "Rejon_nadwórniański", "id": 2040440}, {"name": "Rejon_kosowski", "id": 2040457}, {"name": "Rejon_kałuski", "id": 2040556}, {"name": "Rejon_horodeński", "id": 2040571}, {"name": "Rejon_halicki", "id": 2040611}, {"name": "Rejony_w_Baszkirii", "id": 632586}, {"name": "Rejony_w_Kraju_Krasnojarskim", "id": 5096825}, {"name": "Stacje_i_przystanki_kolejowe_w_rejonie_iwanofrankiwskim", "id": 5080431}, {"name": "Miejscowości_w_rejonie_smoleńskim", "id": 5081737}, {"name": "Miejscowości_rejonu_krasninskiego_w_obwodzie_smoleńskim", "id": 5023115}, {"name": "Miejscowości_rejonu_diemidowskiego", "id": 5046448}, {"name": "Miejscowości_rejonu_rudniańskiego_w_obwodzie_smoleńskim", "id": 5019762}, {"name": "Miejscowości_rejonu_bieżanickiego_w_obwodzie_pskowskim", "id": 4998741}, {"name": "Miejscowości_rejonu_diedowiczskiego_w_obwodzie_pskowskim", "id": 5002623}, {"name": "Miejscowości_rejonu_łokniańskiego_w_obwodzie_pskowskim", "id": 5009431}, {"name": "Stacje_i_przystanki_kolejowe_w_rejonie_kirowskim_(obwód_leningradzki)", "id": 5493281}, {"name": "Stacje_i_przystanki_kolejowe_w_rejonie_wołchowskim", "id": 5494941}, {"name": "Stacje_i_przystanki_kolejowe_w_rejonie_gatczyńskim", "id": 5446935}, {"name": "Stany_Nigerii", "id": 199103}, {"name": "Stany_Stanów_Zjednoczonych", "id": 1161579}, {"name": "Gminy_w_okręgu_Hordaland", "id": 2204991}, {"name": "Departamenty_Kolumbii", "id": 589758}, {"name": "Dystrykty_Ghany", "id": 724466}, {"name": "Dystrykty_Zambii", "id": 2282016}, {"name": "Dystrykty_w_Syrii", "id": 5203562}, {"name": "Azory", "id": 421484}, {"name": "Dystrykt_Bajhang", "id": 2102621}, {"name": "Dystrykt_Achham", "id": 2119546}, {"name": "Dystrykt_Arghakhanchi", "id": 2119547}, {"name": "Dystrykt_Baglung", "id": 2119548}, {"name": "Dystrykt_Baitadi", "id": 2119549}, {"name": "Dystrykt_Banke", "id": 2119552}, {"name": "Dystrykt_Bara", "id": 2119553}, {"name": "Dystrykt_Bardiya", "id": 2119555}, {"name": "Dystrykt_Bhojpur", "id": 2119557}, {"name": "Dystrykt_Chitwan", "id": 2119559}, {"name": "Dystrykt_Dailekh", "id": 2119561}, {"name": "Dystrykt_Dang_Deokhuri", "id": 2119564}, {"name": "Dystrykt_Darchula", "id": 2119565}, {"name": "Dystrykt_Dhading", "id": 2119566}, {"name": "Dystrykt_Dhankuta", "id": 2119568}, {"name": "Dystrykt_Dhanusa", "id": 2119569}, {"name": "Dystrykt_Dholkha", "id": 2119570}, {"name": "Dystrykt_Doti", "id": 2119572}, {"name": "Dystrykt_Gorkha", "id": 2119573}, {"name": "Dystrykt_Gulmi", "id": 2119574}, {"name": "Dystrykt_Ilam", "id": 2119577}, {"name": "Dystrykt_Jhapa", "id": 2119579}, {"name": "Dystrykt_Jumla", "id": 2119580}, {"name": "Dystrykt_Kailali", "id": 2119581}, {"name": "Dystrykt_Kapilvastu", "id": 2119585}, {"name": "Dystrykt_Kaski", "id": 2119586}, {"name": "Dystrykt_Katmandu", "id": 2119588}, {"name": "Dystrykt_Kavrepalanchok", "id": 2119589}, {"name": "Dystrykt_Khotang", "id": 2119590}, {"name": "Dystrykt_Lalitpur", "id": 2119591}, {"name": "Dystrykt_Lamjung", "id": 2119592}, {"name": "Dystrykt_Mahottari", "id": 2119593}, {"name": "Dystrykt_Makwanpur", "id": 2119595}, {"name": "Dystrykt_Morang", "id": 2119597}, {"name": "Dystrykt_Myagdi", "id": 2119600}, {"name": "Dystrykt_Nawalparasi", "id": 2119601}, {"name": "Dystrykt_Nuwakot", "id": 2119602}, {"name": "Dystrykt_Okhaldhunga", "id": 2119604}, {"name": "Dystrykt_Palpa", "id": 2119605}, {"name": "Dystrykt_Panchthar", "id": 2119606}, {"name": "Dystrykt_Parbat", "id": 2119607}, {"name": "Dystrykt_Parsa", "id": 2119608}, {"name": "Dystrykt_Pyuthan", "id": 2119609}, {"name": "Dystrykt_Ramechhap", "id": 2119610}, {"name": "Dystrykt_Rautahat", "id": 2119612}, {"name": "Dystrykt_Rolpa", "id": 2119613}, {"name": "Dystrykt_Rukum", "id": 2119614}, {"name": "Dystrykt_Rupandehi", "id": 2119615}, {"name": "Dystrykt_Salyan", "id": 2119616}, {"name": "Dystrykt_Sankhuwasabha", "id": 2119617}, {"name": "Dystrykt_Saptari", "id": 2119618}, {"name": "Dystrykt_Sarlahi", "id": 2119619}, {"name": "Dystrykt_Sindhuli", "id": 2119620}, {"name": "Dystrykt_Sindhupalchowk", "id": 2119621}, {"name": "Dystrykt_Siraha", "id": 2119622}, {"name": "Dystrykt_Solukhumbu", "id": 2119623}, {"name": "Dystrykt_Sunsari", "id": 2119624}, {"name": "Dystrykt_Surkhet", "id": 2119625}, {"name": "Dystrykt_Syangja", "id": 2119626}, {"name": "Dystrykt_Tanahu", "id": 2119627}, {"name": "Dystrykt_Taplejung", "id": 2119628}, {"name": "Dystrykt_Terhathum", "id": 2119629}, {"name": "Dystrykt_Udayapur", "id": 2119630}, {"name": "Dystrykty_stanu_Maharasztra", "id": 2050794}, {"name": "Dystrykty_stanu_Uttar_Pradesh", "id": 4480506}, {"name": "Dystrykt_Phouvong", "id": 3085759}, {"name": "Dystrykt_Sanamxay", "id": 3086212}, {"name": "Dystrykt_Xaysetha", "id": 4843817}, {"name": "Zabytkowe_kamienice_w_Łodzi", "id": 3935864}, {"name": "Kamienice_przy_ulicy_Piotrkowskiej_w_Łodzi", "id": 3936806}, {"name": "Piłkarze_CD_Marathón", "id": 2184854}, {"name": "Piłkarze_Real_CD_España", "id": 2187164}, {"name": "Piłkarze_Platense_FC", "id": 2136727}, {"name": "Piłkarze_CDS_Vida", "id": 2714689}, {"name": "Piłkarze_FC_Motagua", "id": 2069244}, {"name": "Piłkarze_CD_Olimpia", "id": 2069255}, {"name": "Ludzie_urodzeni_w_Tegucigalpie", "id": 3897771}, {"name": "Piłkarze_CD_Árabe_Unido", "id": 3808013}, {"name": "Piłkarze_San_Francisco_FC", "id": 2337115}, {"name": "Piłkarze_Independiente_La_Chorrera", "id": 4222620}, {"name": "Piłkarze_Tauro_FC", "id": 2809540}, {"name": "Ludzie_urodzeni_w_Panamie_(mieście)", "id": 3897796}, {"name": "Piłkarze_CD_Plaza_Amador", "id": 4211406}, {"name": "Piłkarze_Chorrillo_FC", "id": 4222530}, {"name": "Piłkarze_Sportingu_San_Miguelito", "id": 4222499}, {"name": "Hrabstwa_Kenii", "id": 4751887}, {"name": "Hrabstwa_w_stanie_Nowy_Jork", "id": 551056}, {"name": "Hrabstwa_w_stanie_Alabama", "id": 556010}, {"name": "Hrabstwa_w_stanie_Wisconsin", "id": 585115}, {"name": "Hrabstwa_w_stanie_Ohio", "id": 586946}, {"name": "Hrabstwa_w_stanie_Pensylwania", "id": 613995}, {"name": "Hrabstwa_w_stanie_Kalifornia", "id": 670515}, {"name": "Hrabstwa_w_stanie_Illinois", "id": 702210}, {"name": "Hrabstwa_w_stanie_Floryda", "id": 846489}, {"name": "Hrabstwa_w_stanie_Arkansas", "id": 913748}, {"name": "Hrabstwa_w_stanie_Dakota_Północna", "id": 913750}, {"name": "Hrabstwa_w_stanie_Iowa", "id": 917261}, {"name": "Hrabstwa_w_stanie_Wirginia_Zachodnia", "id": 951064}, {"name": "Hrabstwa_w_stanie_Teksas", "id": 960442}, {"name": "Hrabstwa_w_stanie_Kolorado", "id": 1023228}, {"name": "Hrabstwa_w_stanie_Minnesota", "id": 1033711}, {"name": "Hrabstwa_w_stanie_Tennessee", "id": 1053742}, {"name": "Hrabstwa_w_stanie_Indiana", "id": 1064124}, {"name": "Hrabstwa_w_stanie_Karolina_Północna", "id": 1098266}, {"name": "Hrabstwa_w_stanie_Georgia", "id": 1098388}, {"name": "Hrabstwa_w_stanie_Waszyngton", "id": 1098390}, {"name": "Hrabstwa_w_stanie_Michigan", "id": 1098391}, {"name": "Hrabstwa_w_stanie_Kentucky", "id": 1098392}, {"name": "Hrabstwa_w_stanie_Wirginia", "id": 1100833}, {"name": "Hrabstwa_w_stanie_Karolina_Południowa", "id": 1127226}, {"name": "Hrabstwa_w_stanie_Kansas", "id": 1408654}, {"name": "Hrabstwa_w_stanie_Missouri", "id": 1408692}, {"name": "Hrabstwa_w_stanie_Nebraska", "id": 1410584}, {"name": "Hrabstwa_w_stanie_Oregon", "id": 1410596}, {"name": "Hrabstwa_w_stanie_Dakota_Południowa", "id": 1410624}, {"name": "Hrabstwa_w_stanie_Nowy_Meksyk", "id": 1993046}, {"name": "Hrabstwa_w_stanie_Montana", "id": 2106655}, {"name": "Hrabstwa_w_stanie_Idaho", "id": 2118436}, {"name": "Hrabstwa_w_stanie_Oklahoma", "id": 2150327}, {"name": "Hrabstwa_w_stanie_Missisipi", "id": 2258330}, {"name": "Hrabstwa_Stanów_Zjednoczonych_powstałe_w_1836", "id": 2153501}, {"name": "Hrabstwa_Stanów_Zjednoczonych_powstałe_w_1873", "id": 2153796}, {"name": "Hrabstwa_Stanów_Zjednoczonych_powstałe_w_1850", "id": 2182902}, {"name": "Prawnicy_związani_z_Łodzią", "id": 4356069}, {"name": "Stacje_i_przystanki_kolejowe_w_rejonie_odincowskim", "id": 5474979}, {"name": "Dzielnice_Sztokholmu", "id": 3363523}, {"name": "Dzielnice_i_osiedla_polskich_miast", "id": 1297102}, {"name": "Montmartre", "id": 3611563}, {"name": "Parki_i_ogrody_we_Wrocławiu", "id": 479074}, {"name": "Siatkarze_Cuprum_Lubin", "id": 3185309}, {"name": "Piłkarze_Zagłębia_Lubin", "id": 603430}, {"name": "Piłkarze_ręczni_Zagłębia_Lubin", "id": 1590352}, {"name": "Koszykarze_Turowa_Zgorzelec", "id": 1843513}, {"name": "Miejscowości_w_gminie_Bujwidze", "id": 2949106}, {"name": "Miejscowości_w_gminie_Bezdany", "id": 2924341}, {"name": "Miejscowości_w_gminie_Dukszty", "id": 3089343}, {"name": "Miejscowości_w_gminie_Kowalczuki", "id": 3332256}, {"name": "Miejscowości_w_gminie_Ławaryszki", "id": 3836793}]}