{"name": "Geografia_społeczno-ekonomiczna", "id": 640968, "predecessors": [{"name": "Ekonomia", "id": 64593}, {"name": "Kategorie", "id": 1382275}, {"name": "Ziemia", "id": 140184}], "successors": [{"name": "Geografia_polityczna", "id": 81515}, {"name": "Demografia", "id": 93888}, {"name": "Listy_związane_z_geografią_społeczno-ekonomiczną", "id": 4143708}, {"name": "Historia_odkryć_geograficznych", "id": 70058}, {"name": "Mapy_historyczne", "id": 132558}, {"name": "Geografia_historyczna_starożytności", "id": 171888}, {"name": "Urbanistyka", "id": 69789}, {"name": "Socjologia_miasta", "id": 179818}, {"name": "Opuszczone_wsie_na_Białorusi", "id": 3454797}, {"name": "Opuszczone_wsie_w_Bułgarii", "id": 4333876}, {"name": "Okręgi_przemysłowe", "id": 171157}, {"name": "Geografia_historyczna_Polski", "id": 128128}, {"name": "Geografia_historyczna_Ukrainy", "id": 1369517}, {"name": "Geografia_historyczna_Rosji", "id": 2072298}, {"name": "Ziemia_lubuska", "id": 289544}, {"name": "Prusy", "id": 303703}, {"name": "Historyczne_rejencje_Niemiec", "id": 438240}, {"name": "Krainy_historyczne_Niemiec", "id": 1640922}, {"name": "Górny_Śląsk", "id": 65580}, {"name": "Historia_Śląska", "id": 67867}, {"name": "Kultura_Śląska", "id": 253909}, {"name": "Organizacje_śląskie", "id": 266805}, {"name": "Ludzie_związani_ze_Śląskiem", "id": 754266}, {"name": "Geologia_Sudetów", "id": 1679909}, {"name": "Korona_Sudetów_Polskich", "id": 4171518}, {"name": "Karkonosze", "id": 87250}, {"name": "Góry_Sowie", "id": 143636}, {"name": "Wzgórza_Niemczańsko-Strzelińskie", "id": 466578}, {"name": "Księstwa_śląskie", "id": 479103}, {"name": "Potoki_Gór_Izerskich", "id": 2146096}, {"name": "Szczyty_Rudaw_Janowickich", "id": 1762356}, {"name": "Góry_Stołowe", "id": 159888}, {"name": "Góry_Bystrzyckie_(Sudety)", "id": 371287}, {"name": "Masyw_Śnieżnika", "id": 159855}, {"name": "Góry_Bialskie", "id": 515859}, {"name": "Jaskinie_Wyżyny_Krakowsko-Częstochowskiej", "id": 908867}, {"name": "Sieć_wodna_Wyżyny_Krakowsko-Częstochowskiej", "id": 1470262}, {"name": "Obszary_chronione_Wyżyny_Krakowsko-Częstochowskiej", "id": 1472712}, {"name": "Formacje_skalne_Wyżyny_Krakowsko-Częstochowskiej", "id": 2049659}, {"name": "Turystyka_na_Wyżynie_Krakowsko-Częstochowskiej", "id": 4314800}, {"name": "Doliny_i_wąwozy_Wyżyny_Krakowsko-Częstochowskiej", "id": 4375551}, {"name": "Dawne_komitaty_na_Węgrzech", "id": 680969}, {"name": "Potoki_Karkonoszy", "id": 2145324}, {"name": "Polskie_szczyty_Gór_Izerskich", "id": 1762134}, {"name": "Zrównoważony_rozwój", "id": 1913273}, {"name": "Szczyty_Wzgórz_Niemczańsko-Strzelińskich", "id": 1763235}, {"name": "Regiony_i_krainy_historyczne_Azji", "id": 2944907}, {"name": "Opuszczone_miejscowości_na_Litwie", "id": 3092571}, {"name": "Opuszczone_miejscowości_na_Białorusi", "id": 4750307}, {"name": "Dawne_powiaty_pruskie_(Prowincja_Poznańska)", "id": 3339054}, {"name": "Miasta_starożytne", "id": 1120960}, {"name": "Miasta_i_osady_prehistoryczne", "id": 1345405}, {"name": "Walki_miejskie", "id": 1841675}, {"name": "Listy_miast_według_państw", "id": 2955473}, {"name": "Osiedla_typu_miejskiego_w_Gruzji", "id": 5399185}, {"name": "Osiedla_typu_miejskiego_w_obwodzie_odeskim", "id": 1319842}, {"name": "Osiedla_typu_miejskiego_w_obwodzie_lwowskim", "id": 1343284}, {"name": "Osiedla_typu_miejskiego_w_obwodzie_charkowskim", "id": 1388701}, {"name": "Osiedla_typu_miejskiego_w_obwodzie_żytomierskim", "id": 1389768}, {"name": "Osiedla_typu_miejskiego_w_obwodzie_donieckim", "id": 1395723}, {"name": "Osiedla_typu_miejskiego_w_obwodzie_ługańskim", "id": 1674810}, {"name": "Osiedla_typu_miejskiego_w_Autonomicznej_Republice_Krymu", "id": 3131641}, {"name": "Wielka_kolonizacja", "id": 979830}, {"name": "Wsie_w_Macedonii_Północnej", "id": 606640}, {"name": "Wsie_w_Norwegii", "id": 900160}, {"name": "Wsie_w_Naddniestrzu", "id": 2638423}, {"name": "Wsie_w_Luksemburgu", "id": 5562041}, {"name": "Wsie_w_obwodzie_lwowskim", "id": 1013589}, {"name": "Wsie_w_obwodzie_tarnopolskim", "id": 1043161}, {"name": "Wsie_w_obwodzie_chmielnickim", "id": 1043169}, {"name": "Wsie_w_obwodzie_rówieńskim", "id": 1043173}, {"name": "Wsie_w_obwodzie_wołyńskim", "id": 1043176}, {"name": "Wsie_w_obwodzie_czerkaskim", "id": 1043220}, {"name": "Wsie_w_obwodzie_kijowskim", "id": 1043231}, {"name": "Wsie_w_obwodzie_winnickim", "id": 1043516}, {"name": "Wsie_w_obwodzie_zaporoskim", "id": 1152032}, {"name": "Wsie_w_obwodzie_czernihowskim", "id": 1216683}, {"name": "Wsie_w_obwodzie_chersońskim", "id": 1308555}, {"name": "Wsie_w_obwodzie_żytomierskim", "id": 1419051}, {"name": "Wsie_w_obwodzie_sumskim", "id": 1444097}, {"name": "Wsie_w_obwodzie_kirowohradzkim", "id": 1575370}, {"name": "Wsie_w_obwodzie_odeskim", "id": 1575385}, {"name": "Wsie_w_obwodzie_charkowskim", "id": 1575395}, {"name": "Wsie_w_obwodzie_czerniowieckim", "id": 1575399}, {"name": "Wsie_w_obwodzie_zakarpackim", "id": 1576621}, {"name": "Wsie_w_obwodzie_połtawskim", "id": 1602623}, {"name": "Wsie_w_obwodzie_donieckim", "id": 1757847}, {"name": "Wsie_w_obwodzie_mikołajowskim", "id": 1887039}, {"name": "Wsie_w_obwodzie_dniepropetrowskim", "id": 2322537}, {"name": "Wsie_w_obwodzie_iwanofrankiwskim", "id": 2956072}, {"name": "Wsie_w_Autonomicznej_Republice_Krymu", "id": 3131644}, {"name": "Wsie_w_obwodzie_ługańskim", "id": 3355230}, {"name": "Wsie_w_hrabstwie_Somerset", "id": 1811281}, {"name": "Wsie_w_Kornwalii", "id": 1811282}, {"name": "Wsie_w_hrabstwie_Kent", "id": 1811283}, {"name": "Wsie_w_hrabstwie_Devon", "id": 1816440}, {"name": "Wsie_w_hrabstwie_Bedfordshire", "id": 2106323}, {"name": "Wsie_w_hrabstwie_Berkshire", "id": 2110955}, {"name": "Wsie_w_hrabstwie_Buckinghamshire", "id": 2111320}, {"name": "Wsie_w_hrabstwie_Cambridgeshire", "id": 2112255}, {"name": "Wsie_w_hrabstwie_Cheshire", "id": 2113865}, {"name": "Wsie_w_hrabstwie_Derbyshire", "id": 2115589}, {"name": "Wsie_w_hrabstwie_Dorset", "id": 2120621}, {"name": "Wsie_w_hrabstwie_East_Sussex", "id": 2122535}, {"name": "Wsie_w_hrabstwie_Essex", "id": 2126132}, {"name": "Wsie_w_hrabstwie_Wielki_Manchester", "id": 2128181}, {"name": "Wsie_w_hrabstwie_Hampshire", "id": 2130292}, {"name": "Wsie_w_hrabstwie_Herefordshire", "id": 2134128}, {"name": "Wsie_w_hrabstwie_Hertfordshire", "id": 2135058}, {"name": "Wsie_w_hrabstwie_Lancashire", "id": 2141875}, {"name": "Wsie_w_hrabstwie_Leicestershire", "id": 2146257}, {"name": "Wsie_w_hrabstwie_Lincolnshire", "id": 2151830}, {"name": "Wsie_w_hrabstwie_Norfolk", "id": 2155521}, {"name": "Wsie_w_hrabstwie_North_Yorkshire", "id": 2160925}, {"name": "Wsie_w_hrabstwie_Northamptonshire", "id": 2165995}, {"name": "Wsie_w_hrabstwie_Northumberland", "id": 2168549}, {"name": "Wsie_w_hrabstwie_Nottinghamshire", "id": 2170109}, {"name": "Wsie_w_hrabstwie_Oxfordshire", "id": 2171694}, {"name": "Wsie_w_hrabstwie_Rutland", "id": 2174042}, {"name": "Wsie_w_hrabstwie_Shropshire", "id": 2175287}, {"name": "Wsie_w_hrabstwie_Staffordshire", "id": 2177091}, {"name": "Wsie_w_hrabstwie_Suffolk", "id": 2181994}, {"name": "Wsie_w_hrabstwie_Surrey", "id": 2187181}, {"name": "Wsie_w_hrabstwie_Tyne_and_Wear", "id": 2199029}, {"name": "Wsie_w_hrabstwie_Warwickshire", "id": 2201103}, {"name": "Wsie_w_hrabstwie_West_Sussex", "id": 2210270}, {"name": "Wsie_w_hrabstwie_West_Yorkshire", "id": 2216955}, {"name": "Wsie_w_hrabstwie_Wiltshire", "id": 2228597}, {"name": "Wsie_w_hrabstwie_Worcestershire", "id": 2234911}, {"name": "Wsie_w_hrabstwie_Gloucestershire", "id": 2239054}, {"name": "Wsie_w_hrabstwie_Durham", "id": 2249232}, {"name": "Wsie_w_hrabstwie_East_Riding_of_Yorkshire", "id": 2257552}, {"name": "Wsie_w_hrabstwie_Merseyside", "id": 2260311}, {"name": "Wsie_w_hrabstwie_South_Yorkshire", "id": 2270545}, {"name": "Wsie_w_hrabstwie_West_Midlands", "id": 2273824}, {"name": "Wsie_w_Kumbrii", "id": 2283003}, {"name": "Wsie_na_wyspie_Wight", "id": 2291599}, {"name": "Miejsca_kultu_dawnych_Słowian", "id": 1705655}, {"name": "Kalwarie", "id": 2626574}, {"name": "Święte_miejsca_hinduizmu", "id": 222601}, {"name": "Sanktuaria_chrześcijańskie", "id": 630638}, {"name": "Dawne_polskie_przejścia_graniczne_z_Niemcami", "id": 1190595}, {"name": "Dawne_polskie_przejścia_graniczne_ze_Słowacją", "id": 1190627}, {"name": "Dawne_polskie_przejścia_graniczne_z_Czechami", "id": 2873735}, {"name": "Byłe_polskie_przejścia_graniczne_z_Czechosłowacją", "id": 3276277}, {"name": "Pomorze_Zachodnie", "id": 941623}, {"name": "Władcy_Badenii", "id": 259816}, {"name": "Odznaczeni_Orderem_Lwa_Zeryngeńskiego", "id": 3475905}, {"name": "Odznaczeni_Orderem_Wierności_(Badenia)", "id": 3475930}, {"name": "Miejscowości_na_Łotwie", "id": 595298}, {"name": "Miejscowości_na_Malcie", "id": 873692}, {"name": "Miejscowości_w_Szwajcarii", "id": 898852}, {"name": "Miejscowości_w_Grecji", "id": 904653}, {"name": "Miejscowości_na_Malediwach", "id": 940785}, {"name": "Miejscowości_w_Egipcie", "id": 1058644}, {"name": "Miejscowości_w_Portugalii", "id": 1486432}, {"name": "Miejscowości_na_Cyprze", "id": 2199161}, {"name": "Miejscowości_w_Badenii-Wirtembergii", "id": 5005457}, {"name": "Miejscowości_w_Meklemburgii-Pomorzu_Przednim", "id": 5005464}, {"name": "Miejscowości_w_Nadrenii_Północnej-Westfalii", "id": 5005465}, {"name": "Miejscowości_w_Nadrenii-Palatynacie", "id": 5005466}, {"name": "Miejscowości_w_Saksonii", "id": 5005469}, {"name": "Miejscowości_w_Turyngii", "id": 5005473}, {"name": "Miasta_w_Azerbejdżanie", "id": 485305}, {"name": "Miasta_w_Afganistanie", "id": 134928}, {"name": "Miasta_w_Jordanii", "id": 113558}, {"name": "Wsie_w_Jordanii", "id": 3521846}, {"name": "Miasta_w_Tanzanii", "id": 130382}, {"name": "Miejscowości_w_prowincji_Aragacotn", "id": 4610665}, {"name": "Miejscowości_w_prowincji_Szirak", "id": 4611032}, {"name": "Miejscowości_w_prowincji_Lorri", "id": 4612074}, {"name": "Miejscowości_w_prowincji_Tawusz", "id": 4614967}, {"name": "Miejscowości_w_prowincji_Armawir", "id": 4617190}, {"name": "Miejscowości_w_prowincji_Kotajk", "id": 4619293}, {"name": "Miejscowości_w_prowincji_Ararat", "id": 4620789}, {"name": "Miejscowości_w_prowincji_Gegharkunik", "id": 4621760}, {"name": "Miejscowości_w_prowincji_Wajoc_Dzor", "id": 4622411}, {"name": "Miejscowości_w_prowincji_Sjunik", "id": 4623279}, {"name": "Miasta_w_Wietnamie", "id": 111592}, {"name": "Miasta_w_Mołdawii", "id": 75730}, {"name": "Miejscowości_w_rejonie_Florești", "id": 5140599}, {"name": "Miasteczka_w_Dolnej_Saksonii", "id": 2332872}, {"name": "Miejscowości_w_gminie_Sundsvall", "id": 4925444}, {"name": "Miejscowości_w_gminie_Örnsköldsvik", "id": 4925448}, {"name": "Miejscowości_w_Katalonii", "id": 5018202}, {"name": "Miejscowości_w_Aragonii", "id": 5018306}, {"name": "Wsie_na_Wyspach_Owczych", "id": 2528176}, {"name": "Miasta_w_Kirgistanie", "id": 488855}, {"name": "Miasta_w_Libanie", "id": 134666}, {"name": "Miasta_w_Gabonie", "id": 399292}, {"name": "Miasta_w_Papui-Nowej_Gwinei", "id": 105861}, {"name": "Miasta_w_Izraelu", "id": 94079}, {"name": "Kibuce", "id": 742092}, {"name": "Moszawy", "id": 752130}, {"name": "Wsie_w_Izraelu", "id": 2650995}, {"name": "Wsie_arabskie_w_Palestynie_wyludnione_w_1948_roku_(wojna_domowa)", "id": 2294017}, {"name": "Wsie_arabskie_w_Palestynie_wyludnione_w_1948_roku_(I_wojna_izraelsko-arabska)", "id": 4505630}, {"name": "Wsie_w_dystrykcie_Central", "id": 5203962}, {"name": "Wsie_w_dystrykcie_Kgalagadi", "id": 5203966}, {"name": "Wsie_w_dystrykcie_Kweneng", "id": 5203970}, {"name": "Wsie_w_dystrykcie_Southern", "id": 5203973}, {"name": "Wsie_w_dystrykcie_North_East", "id": 5203975}, {"name": "Wsie_w_dystrykcie_North_West", "id": 5203976}, {"name": "Miejscowości_w_okręgu_Sogn_og_Fjordane", "id": 4071564}, {"name": "Miejscowości_w_muhafazie_Aleppo", "id": 5203487}, {"name": "Miejscowości_w_muhafazie_Idlib", "id": 5203492}, {"name": "Miejscowości_w_muhafazie_Hims", "id": 5203493}, {"name": "Miejscowości_w_muhafazie_Al-Hasaka", "id": 5203495}, {"name": "Miejscowości_w_muhafazie_Hama", "id": 5203499}, {"name": "Miejscowości_w_muhafazie_Ar-Rakka", "id": 5203503}, {"name": "Miejscowości_w_muhafazie_Dajr_az-Zaur", "id": 5203512}, {"name": "Miejscowości_w_muhafazie_Damaszek", "id": 5203516}, {"name": "Miejscowości_w_muhafazie_As-Suwajda", "id": 5203525}, {"name": "Miejscowości_w_muhafazie_Dara", "id": 5203528}, {"name": "Miejscowości_w_muhafazie_Tartus", "id": 5203530}, {"name": "Miejscowości_w_muhafazie_Latakia", "id": 5203532}, {"name": "Miasta_w_Chile", "id": 127198}, {"name": "Miasta_w_Iranie", "id": 131157}, {"name": "Miejscowości_w_Farsie", "id": 4922267}, {"name": "Miejscowości_w_Kurdystanie_(ostan)", "id": 4922278}, {"name": "Miejscowości_w_Kermanie_(ostan)", "id": 4922283}, {"name": "Miejscowości_w_Chuzestanie", "id": 4922287}, {"name": "Miejscowości_w_Azerbejdżanie_Zachodnim", "id": 5303738}, {"name": "Miejscowości_w_Kermanszahu", "id": 5303785}, {"name": "Miasta_w_Kostaryce", "id": 206924}, {"name": "Miasta_w_Demokratycznej_Republice_Konga", "id": 399224}, {"name": "Miasta_w_Czarnogórze", "id": 132122}, {"name": "Miejscowości_w_gminie_Bar", "id": 4675348}, {"name": "Miejscowości_w_gminie_Berane", "id": 4675350}, {"name": "Miejscowości_w_gminie_Bijelo_Polje", "id": 4675351}, {"name": "Miejscowości_w_gminie_Cetynia", "id": 4675353}, {"name": "Miejscowości_w_gminie_Danilovgrad", "id": 4675354}, {"name": "Miejscowości_w_gminie_Kolašin", "id": 4675357}, {"name": "Miejscowości_w_gminie_Kotor", "id": 4675358}, {"name": "Miejscowości_w_gminie_Nikšić", "id": 4675360}, {"name": "Miejscowości_w_gminie_Pljevlja", "id": 4675363}, {"name": "Miejscowości_w_gminie_Plužine", "id": 4675364}, {"name": "Miejscowości_w_gminie_Podgorica", "id": 4675365}, {"name": "Miejscowości_w_gminie_Tuzi", "id": 4675369}, {"name": "Miejscowości_w_gminie_Ulcinj", "id": 4675370}, {"name": "Miasta_w_Jemenie", "id": 94077}, {"name": "Miasta_w_Danii_Południowej", "id": 4355307}, {"name": "Wsie_w_prowincji_Borneo_Południowe", "id": 3556468}, {"name": "Miasta_w_Surinamie", "id": 495929}, {"name": "Miejscowości_w_dystrykcie_Brczko", "id": 4769787}, {"name": "Miasta_w_Panamie", "id": 94112}, {"name": "Miasta_w_Brandenburgii", "id": 513906}, {"name": "Miasta_w_Dolnej_Saksonii", "id": 513908}, {"name": "Miasta_w_Hesji", "id": 336325}, {"name": "Miasta_w_Saksonii-Anhalcie", "id": 3328570}, {"name": "Miasta_w_Szlezwiku-Holsztynie", "id": 1667171}, {"name": "Miasta_w_Sudanie_Południowym", "id": 1558932}, {"name": "Miasta_w_Namibii", "id": 179370}, {"name": "Miasta_w_Czadzie", "id": 127800}, {"name": "Wsie_w_Osetii_Południowej", "id": 5057596}, {"name": "Miasta_w_Omanie", "id": 161791}, {"name": "Miasta_na_Sri_Lance", "id": 297617}, {"name": "Miasta_w_Bangladeszu", "id": 443320}, {"name": "Miasta_na_Filipinach", "id": 187131}, {"name": "Miasta_w_Tajlandii", "id": 111575}, {"name": "Miasta_w_Kolumbii", "id": 467200}, {"name": "Miasta_w_Boliwii", "id": 127737}, {"name": "Miasta_w_Peru", "id": 200699}, {"name": "Miasta_w_Ekwadorze", "id": 326247}, {"name": "Miasta_w_Paragwaju", "id": 209139}, {"name": "Miasta_w_Urugwaju", "id": 101936}, {"name": "Miasta_w_Hondurasie", "id": 118609}, {"name": "Miasta_w_Nikaragui", "id": 155020}, {"name": "Miasta_w_Salwadorze", "id": 207931}, {"name": "Miasta_na_Haiti", "id": 141922}, {"name": "Miasta_na_Kubie", "id": 101934}, {"name": "Miasta_w_Dominikanie", "id": 432957}, {"name": "Miasta_na_Jamajce", "id": 477001}, {"name": "Miasta_w_Algierii", "id": 130349}, {"name": "Miasta_w_Ghanie", "id": 447971}, {"name": "Miasta_w_Gwinei_Bissau", "id": 123024}, {"name": "Miasta_w_Angoli", "id": 115609}, {"name": "Miasta_w_Kamerunie", "id": 134735}, {"name": "Miasta_na_Madagaskarze", "id": 138375}, {"name": "Miasta_w_Zambii", "id": 138386}, {"name": "Miasta_w_Beninie", "id": 200534}, {"name": "Miasta_w_Kenii", "id": 138384}, {"name": "Miasta_w_Gwinei", "id": 138367}, {"name": "Miasta_w_Malawi", "id": 538261}, {"name": "Miasta_w_Senegalu", "id": 124460}, {"name": "Miasta_w_Burkinie_Faso", "id": 2816540}, {"name": "Miasta_w_Republice_Środkowoafrykańskiej", "id": 577717}, {"name": "Miasta_w_Zimbabwe", "id": 259884}, {"name": "Miasta_w_Sierra_Leone", "id": 122389}, {"name": "Miasta_w_Mali", "id": 114987}, {"name": "Miasta_w_Wybrzeżu_Kości_Słoniowej", "id": 579419}, {"name": "Miasta_w_Kongu", "id": 1130531}, {"name": "Miasta_w_Maroku", "id": 130403}, {"name": "Miasta_w_Mauretanii", "id": 124463}, {"name": "Miasta_w_Mozambiku", "id": 115573}, {"name": "Miasta_na_Mauritiusie", "id": 121449}, {"name": "Miasta_w_Ugandzie", "id": 526441}, {"name": "Miasta_w_Serbii", "id": 71734}, {"name": "Miasta_w_Turcji", "id": 71816}, {"name": "Miasta_na_Łotwie", "id": 85259}, {"name": "Miasta_w_Nigrze", "id": 115572}, {"name": "Miasta_w_Słowenii", "id": 121108}, {"name": "Miasta_w_Macedonii_Północnej", "id": 124833}, {"name": "Miasta_w_Libii", "id": 131163}, {"name": "Miasta_w_Tunezji", "id": 200536}, {"name": "Miasta_w_komitacie_Pest", "id": 5381412}, {"name": "Miasta_w_Regionie_Stołecznym", "id": 4355308}, {"name": "Miasta_w_Jutlandii_Środkowej", "id": 4355323}, {"name": "Miasta_w_Jutlandii_Północnej", "id": 4355324}, {"name": "Miasta_w_Zelandii", "id": 4355325}, {"name": "Miasta_w_stanie_São_Paulo", "id": 704664}, {"name": "Miasta_w_stanie_Bahia", "id": 704670}, {"name": "Miasta_w_stanie_Santa_Catarina", "id": 704675}, {"name": "Miasta_w_stanie_Pará", "id": 704681}, {"name": "Miasta_w_stanie_Minas_Gerais", "id": 704692}, {"name": "Miasta_w_stanie_Maranhão", "id": 704693}, {"name": "Miasta_w_stanie_Rio_de_Janeiro", "id": 704709}, {"name": "Miasta_w_stanie_Rondônia", "id": 704718}, {"name": "Miasta_w_stanie_Rio_Grande_do_Sul", "id": 704720}, {"name": "Miasta_w_stanie_Mato_Grosso", "id": 704724}, {"name": "Miasta_w_stanie_Mato_Grosso_do_Sul", "id": 704725}, {"name": "Miasta_w_stanie_Amazonas", "id": 704729}, {"name": "Miasta_w_stanie_Espírito_Santo", "id": 704740}, {"name": "Miasta_w_stanie_Parana", "id": 2537850}, {"name": "Miasta_w_Bawarii", "id": 96958}, {"name": "Miasta_w_Badenii-Wirtembergii", "id": 288696}, {"name": "Miasta_w_Saksonii", "id": 298250}, {"name": "Miasta_w_Nadrenii_Północnej-Westfalii", "id": 311092}, {"name": "Miasta_w_Meklemburgii-Pomorzu_Przednim", "id": 322889}, {"name": "Miasta_w_Turyngii", "id": 513907}, {"name": "Miasta_w_Nadrenii-Palatynacie", "id": 513918}, {"name": "Dawne_miasta_w_Niemczech", "id": 1766348}, {"name": "Miasta_w_prowincji_Geldria", "id": 4183261}, {"name": "Miasta_w_prowincji_Brabancja_Północna", "id": 4183266}, {"name": "Miasta_w_prowincji_Holandia_Północna", "id": 4183267}, {"name": "Miasta_w_prowincji_Holandia_Południowa", "id": 4183271}, {"name": "Miasta_zamknięte", "id": 737530}, {"name": "Herby_miast_Federacji_Rosyjskiej", "id": 1046986}, {"name": "Dawne_miasta_w_Rosji", "id": 5389821}, {"name": "Miasta_w_Regionie_Attyka", "id": 5382916}, {"name": "Miasta_w_Irlandii_Północnej", "id": 587154}, {"name": "Miasta_w_hrabstwie_Lancashire", "id": 742005}, {"name": "Miasta_w_hrabstwie_Wielki_Manchester", "id": 742012}, {"name": "Miasta_w_hrabstwie_Kent", "id": 742124}, {"name": "Miasta_w_hrabstwie_Essex", "id": 742143}, {"name": "Miasta_w_hrabstwie_Somerset", "id": 742158}, {"name": "Miasta_w_Kornwalii", "id": 742187}, {"name": "Miasta_w_hrabstwie_Lincolnshire", "id": 742192}, {"name": "Miasta_w_hrabstwie_West_Yorkshire", "id": 742408}, {"name": "Miasta_w_hrabstwie_Gloucestershire", "id": 742657}, {"name": "Miasta_w_hrabstwie_Devon", "id": 742679}, {"name": "Miasta_w_hrabstwie_North_Yorkshire", "id": 743256}, {"name": "Miasta_ze_statusem_city_w_Anglii", "id": 4072611}, {"name": "Miasta_w_dystrykcie_Leiria", "id": 1463784}, {"name": "Miasta_w_dystrykcie_Vila_Real", "id": 1463794}, {"name": "Miasta_w_dystrykcie_Viseu", "id": 1463804}, {"name": "Miasta_w_Katalonii", "id": 2929028}, {"name": "Miasta_w_Walencji_(wspólnota_autonomiczna)", "id": 4176640}, {"name": "Miasta_w_Kastylii-La_Mancha", "id": 4176641}, {"name": "Miasta_w_Kastylii_i_León", "id": 4176644}, {"name": "Miasta_w_Galicji", "id": 4176648}, {"name": "Miasta_we_wspólnocie_autonomicznej_Madrytu", "id": 4176655}, {"name": "Miasta_w_Andaluzji", "id": 4176656}, {"name": "Herby_miast_białoruskich", "id": 965322}, {"name": "Miasta_w_kraju_hradeckim", "id": 4173697}, {"name": "Miasta_w_kraju_karlowarskim", "id": 4173710}, {"name": "Miasta_w_kraju_libereckim", "id": 4173731}, {"name": "Miasta_w_kraju_morawsko-śląskim", "id": 4173749}, {"name": "Miasta_w_kraju_pardubickim", "id": 4173769}, {"name": "Miasta_w_kraju_pilzneńskim", "id": 4173770}, {"name": "Miasta_w_kraju_południowoczeskim", "id": 4173771}, {"name": "Miasta_w_kraju_południowomorawskim", "id": 4173772}, {"name": "Miasta_w_kraju_środkowoczeskim", "id": 4173773}, {"name": "Miasta_w_kraju_usteckim", "id": 4173774}, {"name": "Miasta_w_kraju_Wysoczyna", "id": 4173776}, {"name": "Dawne_miasta_w_Czechach", "id": 5389914}, {"name": "Miasta_w_Dolnej_Austrii", "id": 1580416}, {"name": "Miasta_w_Styrii", "id": 1580418}, {"name": "Miasta_w_Górnej_Austrii", "id": 1580439}, {"name": "Miasta_w_prefekturze_Aichi", "id": 1163607}, {"name": "Miasta_w_prefekturze_Gifu", "id": 1225966}, {"name": "Miasta_w_prefekturze_Aomori", "id": 2322186}, {"name": "Miasta_w_prefekturze_Chiba", "id": 2322189}, {"name": "Miasta_w_prefekturze_Fukuoka", "id": 2322206}, {"name": "Miasta_w_prefekturze_Fukushima", "id": 2322209}, {"name": "Miasta_w_prefekturze_Saitama", "id": 2322211}, {"name": "Miasta_w_prefekturze_Osaka", "id": 2322222}, {"name": "Miasta_w_prefekturze_Hyōgo", "id": 2322230}, {"name": "Miasta_w_prefekturze_Nagano", "id": 2322321}, {"name": "Miasta_w_prefekturze_Hokkaido", "id": 2322332}, {"name": "Miasta_w_prefekturze_Ibaraki", "id": 2322339}, {"name": "Miasta_w_prefekturze_Shizuoka", "id": 2322350}, {"name": "Miasta_w_prefekturze_Kanagawa", "id": 2322433}, {"name": "Miasta_w_prefekturze_Kagoshima", "id": 2322478}, {"name": "Miasta_w_prefekturze_Kumamoto", "id": 2322485}, {"name": "Miasta_w_prefekturze_Miyagi", "id": 2322486}, {"name": "Miasta_w_prefekturze_Yamagata", "id": 2322505}, {"name": "Miasta_w_stanie_Bengal_Zachodni", "id": 988616}, {"name": "Miasta_w_stanie_Karnataka", "id": 988761}, {"name": "Miasta_w_stanie_Maharasztra", "id": 2050791}, {"name": "Miasta_w_stanie_Tamilnadu", "id": 3048865}, {"name": "Miasta_w_stanie_Veracruz", "id": 1699431}, {"name": "Miasta_w_stanie_Meksyk", "id": 1699485}, {"name": "Miasta_w_stanie_Jalisco", "id": 1699507}, {"name": "Miasta_w_muhafazie_Latakia", "id": 4103738}, {"name": "Miasta_w_muhafazie_Dara", "id": 4103739}, {"name": "Miasta_w_muhafazie_Idlib", "id": 4103744}, {"name": "Miasta_w_muhafazie_Aleppo", "id": 4103746}, {"name": "Miasta_w_muhafazie_Damaszek", "id": 4103756}, {"name": "Miasta_w_prowincji_Buenos_Aires", "id": 1572112}, {"name": "Miasta_w_prowincji_Misiones", "id": 1572158}, {"name": "Miasta_w_prowincji_Santa_Fe", "id": 1572186}, {"name": "Miasta_w_Federacji_Bośni_i_Hercegowiny", "id": 1573000}, {"name": "Miasta_w_Republice_Serbskiej", "id": 1573005}, {"name": "Miasta_w_regionie_Otago", "id": 2824218}, {"name": "Miasta_w_regionie_Canterbury", "id": 2824219}, {"name": "Miasta_w_regionie_Waikato", "id": 2824222}, {"name": "Miasta_w_Regionie_Amhara", "id": 1521842}, {"name": "Miasta_w_Regionie_Oromia", "id": 1521846}, {"name": "Miasta_w_Pendżabie_(Pakistan)", "id": 1512659}, {"name": "Miasta_w_departamencie_Huehuetenango", "id": 2921001}, {"name": "Miasta_w_stanie_Miranda", "id": 1680067}, {"name": "Miasta_w_stanie_Floryda", "id": 482582}, {"name": "Miasta_w_stanie_Alabama", "id": 482588}, {"name": "Miasta_w_stanie_Alaska", "id": 485288}, {"name": "Miasta_w_stanie_Arkansas", "id": 485296}, {"name": "Miasta_w_stanie_Connecticut", "id": 485297}, {"name": "Miasta_w_stanie_Dakota_Południowa", "id": 485300}, {"name": "Miasta_w_stanie_Delaware", "id": 485306}, {"name": "Miasta_w_stanie_Idaho", "id": 485310}, {"name": "Miasta_w_stanie_Kentucky", "id": 485314}, {"name": "Miasta_w_stanie_Luizjana", "id": 485319}, {"name": "Miasta_w_stanie_Kolorado", "id": 485322}, {"name": "Miasta_w_stanie_Teksas", "id": 485342}, {"name": "Miasta_w_stanie_Maine", "id": 485348}, {"name": "Miasta_w_stanie_Maryland", "id": 485349}, {"name": "Miasta_w_stanie_Massachusetts", "id": 485351}, {"name": "Miasta_w_stanie_Michigan", "id": 485352}, {"name": "Miasta_w_stanie_Minnesota", "id": 485353}, {"name": "Miasta_w_stanie_Montana", "id": 485354}, {"name": "Miasta_w_stanie_New_Hampshire", "id": 485356}, {"name": "Miasta_w_stanie_Oregon", "id": 485358}, {"name": "Miasta_w_stanie_Karolina_Południowa", "id": 485361}, {"name": "Miasta_w_stanie_Tennessee", "id": 485362}, {"name": "Miasta_w_stanie_Utah", "id": 485364}, {"name": "Miasta_w_stanie_Wirginia", "id": 485367}, {"name": "Miasta_w_stanie_Wisconsin", "id": 485369}, {"name": "Miasta_w_stanie_Wyoming", "id": 485371}, {"name": "Miasta_w_stanie_Nowy_Jork", "id": 485374}, {"name": "Miasta_w_stanie_Georgia", "id": 485376}, {"name": "Miasta_w_stanie_Illinois", "id": 485378}, {"name": "Miasta_w_stanie_Indiana", "id": 485379}, {"name": "Miasta_w_stanie_Iowa", "id": 485394}, {"name": "Miasta_w_stanie_Karolina_Północna", "id": 485395}, {"name": "Miasta_w_stanie_New_Jersey", "id": 485399}, {"name": "Miasta_w_stanie_Nowy_Meksyk", "id": 485401}, {"name": "Miasta_w_stanie_Ohio", "id": 485403}, {"name": "Miasta_w_stanie_Pensylwania", "id": 485404}, {"name": "Miasta_w_stanie_Waszyngton", "id": 485409}, {"name": "Miasta_w_stanie_Arizona", "id": 485420}, {"name": "Miasta_w_stanie_Missouri", "id": 485421}, {"name": "Miasta_w_stanie_Oklahoma", "id": 485422}, {"name": "Miasta_w_stanie_Kansas", "id": 485425}, {"name": "Miasta_w_stanie_Nebraska", "id": 485428}, {"name": "Miasta_w_stanie_Missisipi", "id": 499382}, {"name": "Miasta_w_stanie_Rhode_Island", "id": 499385}, {"name": "Miasta_w_stanie_Dakota_Północna", "id": 510368}, {"name": "Miasta_w_stanie_Wirginia_Zachodnia", "id": 826746}, {"name": "Stolice_stanów_Stanów_Zjednoczonych", "id": 1161623}, {"name": "Miasta_w_hrabstwie_Los_Angeles", "id": 2298983}, {"name": "Miasta_w_hrabstwie_Orange", "id": 2299288}, {"name": "Miasta_w_obwodzie_moskiewskim", "id": 553008}, {"name": "Miasta_w_obwodzie_swierdłowskim", "id": 701699}, {"name": "Dystrykt_Dhankuta", "id": 2119568}, {"name": "Dystrykt_Ilam", "id": 2119577}, {"name": "Dystrykt_Jhapa", "id": 2119579}, {"name": "Dystrykt_Morang", "id": 2119597}, {"name": "Dystrykt_Sankhuwasabha", "id": 2119617}, {"name": "Dystrykt_Sunsari", "id": 2119624}, {"name": "Dystrykt_Udayapur", "id": 2119630}, {"name": "Miasta_w_obwodzie_donieckim", "id": 702599}, {"name": "Miasta_w_obwodzie_lwowskim", "id": 702617}, {"name": "Miasta_w_obwodzie_ługańskim", "id": 1674791}, {"name": "Podział_administracyjny_Sydney", "id": 1670931}, {"name": "Podział_administracyjny_Melbourne", "id": 1781211}, {"name": "Podział_aglomeracji_Sydney", "id": 1741377}, {"name": "Miasta_w_regionie_Prowansja-Alpy-Lazurowe_Wybrzeże", "id": 5381637}, {"name": "Miasta_w_regionie_Owernia-Rodan-Alpy", "id": 5381639}, {"name": "Miasta_w_regionie_Île-de-France", "id": 5381652}, {"name": "Miasta_w_regionie_Hauts-de-France", "id": 5381654}, {"name": "Miasta_w_regionie_Nowa_Akwitania", "id": 5381658}, {"name": "Miasta_w_Portoryko", "id": 937388}, {"name": "Miasta_w_okręgu_Trøndelag", "id": 4807511}, {"name": "Wsie_w_muhafazie_Ramallah_i_Al-Bira", "id": 4366543}]}